{
  "reservations": [
    {
      "id": 1,
      "name": "최유리",
      "departmentId": 1,
      "date": "2025-01-10",
      "time": "09:00 AM"
    },
    {
      "id": 2,
      "name": "박지훈",
      "departmentId": 2,
      "date": "2025-01-10",
      "time": "10:00 AM"
    },
    {
      "id": 3,
      "name": "이승기",
      "departmentId": 3,
      "date": "2025-01-10",
      "time": "11:00 AM"
    },
    {
      "id": 4,
      "name": "김소연",
      "departmentId": 4,
      "date": "2025-01-10",
      "time": "01:00 PM"
    },
    {
      "id": 5,
      "name": "오지연",
      "departmentId": 5,
      "date": "2025-01-10",
      "time": "02:00 PM"
    },
    {
      "id": 6,
      "name": "박성민",
      "departmentId": 6,
      "date": "2025-01-10",
      "time": "03:00 PM"
    },
    {
      "id": 7,
      "name": "김나현",
      "departmentId": 7,
      "date": "2025-01-10",
      "time": "04:00 PM"
    },
    {
      "id": 8,
      "name": "이정훈",
      "departmentId": 8,
      "date": "2025-01-10",
      "time": "05:00 PM"
    },
    {
      "id": 9,
      "name": "윤아름",
      "departmentId": 9,
      "date": "2025-01-11",
      "time": "09:00 AM"
    },
    {
      "id": 10,
      "name": "최준호",
      "departmentId": 10,
      "date": "2025-01-11",
      "time": "10:00 AM"
    }
  ]
}
